Metadata-Version: 2.4
Name: ovos_ocp_rss_plugin
Version: 0.1.2
Summary: OCP rss feed stream extractor plugin
Home-page: https://github.com/OpenVoiceOS/ovos-ocp-rss-plugin
Author: JarbasAi
Author-email: jarbasai@mailfence.com
License: Apache-2.0
Keywords: ovos ocp plugin
License-File: LICENSE
Requires-Dist: ovos-plugin-manager<3.0.0,>=0.0.1
Requires-Dist: feedparser
Dynamic: author
Dynamic: author-email
Dynamic: home-page
Dynamic: keywords
Dynamic: license
Dynamic: license-file
Dynamic: requires-dist
Dynamic: summary
